[
    {
        "path": "404.html",
        "type": "file",
        "md5": "a64a172888d1aab22370c223ffa8a363"
    },
    {
        "path": "assets",
        "type": "directory",
        "md5": false
    },
    {
        "path": "assets/css",
        "type": "directory",
        "md5": false
    },
    {
        "path": "/assets/css/editor.css",
        "type": "file",
        "md5": "78ecc15acbbcb7c3184fcf8bf729841d"
    },
    {
        "path": "/assets/css/main.css",
        "type": "file",
        "md5": "55fc1708c5de1d7eb47505fda135b4e0"
    },
    {
        "path": "/assets/css/p-slider.css",
        "type": "file",
        "md5": "5ac81efd5deb502fc3388d1c572c5e3c"
    },
    {
        "path": "/assets/css/photoswipe.css",
        "type": "file",
        "md5": "ffb247881cd6f611d007fd4a96b7b16a"
    },
    {
        "path": "/assets/css/style.css",
        "type": "file",
        "md5": "8c03707ad04deb16faa8979cb7841088"
    },
    {
        "path": "assets/js",
        "type": "directory",
        "md5": false
    },
    {
        "path": "/assets/js/jquery-3.2.1.slim.min.js",
        "type": "file",
        "md5": "5f48fc77cac90c4778fa24ec9c57f37d"
    },
    {
        "path": "/assets/js/lazysizes.min.js",
        "type": "file",
        "md5": "300b16f1c14e1537e6b064f464ab33b1"
    },
    {
        "path": "/assets/js/photoswipe-ui-default.min.js",
        "type": "file",
        "md5": "c061a13816b98ce8c8a7ffb2e62dc403"
    },
    {
        "path": "/assets/js/photoswipe.min.js",
        "type": "file",
        "md5": "90d5a5ff4789f25f79840f95fc089c0e"
    },
    {
        "path": "/assets/js/scripts.js",
        "type": "file",
        "md5": "3987cafeab433f1b24bb96932b768ec3"
    },
    {
        "path": "/assets/js/scripts.min.js",
        "type": "file",
        "md5": "5977caa3bd6c30eab5c559ded3288d58"
    },
    {
        "path": "/assets/js/svg-fix.js",
        "type": "file",
        "md5": "7c0d2bb7276904b382e80bf2d85e8a96"
    },
    {
        "path": "/assets/js/svg2js.js",
        "type": "file",
        "md5": "4af0a29f761adb48642f1e0aac294315"
    },
    {
        "path": "assets/svg",
        "type": "directory",
        "md5": false
    },
    {
        "path": "/assets/svg/gallery-icons-dark.svg",
        "type": "file",
        "md5": "452594838e74a3df91ad4a20cf53c831"
    },
    {
        "path": "/assets/svg/gallery-icons-light.svg",
        "type": "file",
        "md5": "ca77079e0fe8270a7447d7f1f5d543b0"
    },
    {
        "path": "/assets/svg/search.svg",
        "type": "file",
        "md5": "a5bb83b82b98f41b359f20dbf9db6e44"
    },
    {
        "path": "/assets/svg/svg-map.svg",
        "type": "file",
        "md5": "7456a9e21fb0b8aecf433388fca58394"
    },
    {
        "path": "authors",
        "type": "directory",
        "md5": false
    },
    {
        "path": "authors/leon",
        "type": "directory",
        "md5": false
    },
    {
        "path": "/authors/leon/index.html",
        "type": "file",
        "md5": "63694bb38f6570c472293993227ba5e0"
    },
    {
        "path": "index.html",
        "type": "file",
        "md5": "4e0d0e411caf0d9f4537fe338814a2d2"
    },
    {
        "path": "media",
        "type": "directory",
        "md5": false
    },
    {
        "path": "media/posts",
        "type": "directory",
        "md5": false
    },
    {
        "path": "media/posts/1",
        "type": "directory",
        "md5": false
    },
    {
        "path": "/media/posts/1/IMG_4858.jpg",
        "type": "file",
        "md5": "24b66e04a7f133be85e40a516df1cb65"
    },
    {
        "path": "/media/posts/1/IMG_4862-2.jpg",
        "type": "file",
        "md5": "02a3ef1a4e950280f3d87a25a13e2764"
    },
    {
        "path": "/media/posts/1/IMG_4872-2.jpg",
        "type": "file",
        "md5": "84d2faec7ad8bb9c9f8298f7cb96efb6"
    },
    {
        "path": "/media/posts/1/IMG_4872.jpg",
        "type": "file",
        "md5": "84d2faec7ad8bb9c9f8298f7cb96efb6"
    },
    {
        "path": "/media/posts/1/IMG_4873.jpg",
        "type": "file",
        "md5": "4b7cc4e82e3fb4a0d123d1f89cc2e52e"
    },
    {
        "path": "/media/posts/1/IMG_4874.jpg",
        "type": "file",
        "md5": "976aa0d1ed9d5afe692a8ea16263c91c"
    },
    {
        "path": "/media/posts/1/IMG_4876.jpg",
        "type": "file",
        "md5": "0143d874b8a7ecb61ddb6ea5bf3fbd3f"
    },
    {
        "path": "/media/posts/1/IMG_4879.jpg",
        "type": "file",
        "md5": "efadfac5822a33dcbfdcde293d971ab6"
    },
    {
        "path": "/media/posts/1/IMG_4880.jpg",
        "type": "file",
        "md5": "ca496c48fea3525c956d8b094258c61b"
    },
    {
        "path": "/media/posts/1/IMG_4882.jpg",
        "type": "file",
        "md5": "224089f090d0ae5a632d34472b5b43a9"
    },
    {
        "path": "/media/posts/1/IMG_4884.jpg",
        "type": "file",
        "md5": "3e3f10669b203892cd3e0029a8bf6941"
    },
    {
        "path": "media/posts/1/responsive",
        "type": "directory",
        "md5": false
    },
    {
        "path": "/media/posts/1/responsive/IMG_4858-lg.jpg",
        "type": "file",
        "md5": "75bdbc75afebe2f092ecdc8158be8616"
    },
    {
        "path": "/media/posts/1/responsive/IMG_4858-md.jpg",
        "type": "file",
        "md5": "ff2cb57c22f4bc1dc171b3a0cf36b7e3"
    },
    {
        "path": "/media/posts/1/responsive/IMG_4858-sm.jpg",
        "type": "file",
        "md5": "4aba97815037788082639d8a50c6945b"
    },
    {
        "path": "/media/posts/1/responsive/IMG_4858-xs.jpg",
        "type": "file",
        "md5": "a4b280cadb6893f3dbb8c280b5291e12"
    },
    {
        "path": "/media/posts/1/responsive/IMG_4862-2-lg.jpg",
        "type": "file",
        "md5": "d3e76e83a483f73dcea9ad2bd51e4749"
    },
    {
        "path": "/media/posts/1/responsive/IMG_4862-2-md.jpg",
        "type": "file",
        "md5": "d224266ce2d132b7cfcdc7f53667119d"
    },
    {
        "path": "/media/posts/1/responsive/IMG_4862-2-sm.jpg",
        "type": "file",
        "md5": "f120b886d627460f448a23879081fe4a"
    },
    {
        "path": "/media/posts/1/responsive/IMG_4862-2-xs.jpg",
        "type": "file",
        "md5": "7fbb00b637cbb18ae530c4d414e1aed2"
    },
    {
        "path": "/media/posts/1/responsive/IMG_4872-2-lg.jpg",
        "type": "file",
        "md5": "9417fd22fd5d1937de8b0b65415470f9"
    },
    {
        "path": "/media/posts/1/responsive/IMG_4872-2-md.jpg",
        "type": "file",
        "md5": "56f3ed3dad74388e5f20d838b8afd5c1"
    },
    {
        "path": "/media/posts/1/responsive/IMG_4872-2-sm.jpg",
        "type": "file",
        "md5": "5721c4522a18f056a5939f75718e1752"
    },
    {
        "path": "/media/posts/1/responsive/IMG_4872-2-xs.jpg",
        "type": "file",
        "md5": "fb01918e86f7327b0eae9be691e9e56e"
    },
    {
        "path": "/media/posts/1/responsive/IMG_4872-2xl.jpg",
        "type": "file",
        "md5": "c174979f137c9f5d6b7b2519a44c1484"
    },
    {
        "path": "/media/posts/1/responsive/IMG_4872-3xl.jpg",
        "type": "file",
        "md5": "8bb3c21ab114d952c81ab68fda6a69cd"
    },
    {
        "path": "/media/posts/1/responsive/IMG_4872-lg.jpg",
        "type": "file",
        "md5": "9417fd22fd5d1937de8b0b65415470f9"
    },
    {
        "path": "/media/posts/1/responsive/IMG_4872-md.jpg",
        "type": "file",
        "md5": "56f3ed3dad74388e5f20d838b8afd5c1"
    },
    {
        "path": "/media/posts/1/responsive/IMG_4872-sm.jpg",
        "type": "file",
        "md5": "5721c4522a18f056a5939f75718e1752"
    },
    {
        "path": "/media/posts/1/responsive/IMG_4872-xl.jpg",
        "type": "file",
        "md5": "9f2721a477fcb91987a37b821cf90dd1"
    },
    {
        "path": "/media/posts/1/responsive/IMG_4872-xs.jpg",
        "type": "file",
        "md5": "fb01918e86f7327b0eae9be691e9e56e"
    },
    {
        "path": "/media/posts/1/responsive/IMG_4873-lg.jpg",
        "type": "file",
        "md5": "8ac32712e53329d0c09d3d2766d7dac3"
    },
    {
        "path": "/media/posts/1/responsive/IMG_4873-md.jpg",
        "type": "file",
        "md5": "da41277aaf968a3bcc093354de79481c"
    },
    {
        "path": "/media/posts/1/responsive/IMG_4873-sm.jpg",
        "type": "file",
        "md5": "ee218206c493174415a3d36090560534"
    },
    {
        "path": "/media/posts/1/responsive/IMG_4873-xs.jpg",
        "type": "file",
        "md5": "8b585f2b5b689e852978054196f45418"
    },
    {
        "path": "/media/posts/1/responsive/IMG_4874-lg.jpg",
        "type": "file",
        "md5": "15fd054c3dc25297404b5af0c5d9feaf"
    },
    {
        "path": "/media/posts/1/responsive/IMG_4874-md.jpg",
        "type": "file",
        "md5": "34edaa37426e17558c076cf963cd359a"
    },
    {
        "path": "/media/posts/1/responsive/IMG_4874-sm.jpg",
        "type": "file",
        "md5": "8a6625d683304621ea785e71c69eb4cc"
    },
    {
        "path": "/media/posts/1/responsive/IMG_4874-xs.jpg",
        "type": "file",
        "md5": "b69c5a67ce03dc6489c27bbec9057ede"
    },
    {
        "path": "/media/posts/1/responsive/IMG_4876-lg.jpg",
        "type": "file",
        "md5": "47f2f69500924e35449d8c1ab59a8b44"
    },
    {
        "path": "/media/posts/1/responsive/IMG_4876-md.jpg",
        "type": "file",
        "md5": "f8951af432c78f3e2ede26df70960a82"
    },
    {
        "path": "/media/posts/1/responsive/IMG_4876-sm.jpg",
        "type": "file",
        "md5": "466add34919885986ce36cae72618e40"
    },
    {
        "path": "/media/posts/1/responsive/IMG_4876-xs.jpg",
        "type": "file",
        "md5": "99ac1d682fd895c1b281026a863b30b3"
    },
    {
        "path": "/media/posts/1/responsive/IMG_4879-lg.jpg",
        "type": "file",
        "md5": "f939f502625ec3985e35eccf0f9a2721"
    },
    {
        "path": "/media/posts/1/responsive/IMG_4879-md.jpg",
        "type": "file",
        "md5": "fc7fbd66162ff230c02b931c769af910"
    },
    {
        "path": "/media/posts/1/responsive/IMG_4879-sm.jpg",
        "type": "file",
        "md5": "d4c06c54e730a30050cd47986f447d1f"
    },
    {
        "path": "/media/posts/1/responsive/IMG_4879-xs.jpg",
        "type": "file",
        "md5": "e28bdb01b855dead51968afe8b50924b"
    },
    {
        "path": "/media/posts/1/responsive/IMG_4880-lg.jpg",
        "type": "file",
        "md5": "f180c4ba2045d52d782c07a4e1963f4a"
    },
    {
        "path": "/media/posts/1/responsive/IMG_4880-md.jpg",
        "type": "file",
        "md5": "404bf3f8eb1aac0fd862fa21947ac168"
    },
    {
        "path": "/media/posts/1/responsive/IMG_4880-sm.jpg",
        "type": "file",
        "md5": "85373366d19869830bdddea5b0c22cc9"
    },
    {
        "path": "/media/posts/1/responsive/IMG_4880-xs.jpg",
        "type": "file",
        "md5": "f080622ae5ca5f34098012f609967212"
    },
    {
        "path": "/media/posts/1/responsive/IMG_4882-lg.jpg",
        "type": "file",
        "md5": "4ae5a802389f4c992e45875858241dac"
    },
    {
        "path": "/media/posts/1/responsive/IMG_4882-md.jpg",
        "type": "file",
        "md5": "289b35b7d896cccbdef0fc9bbb779edd"
    },
    {
        "path": "/media/posts/1/responsive/IMG_4882-sm.jpg",
        "type": "file",
        "md5": "411feaa1cea6b92c441c36add0d201e5"
    },
    {
        "path": "/media/posts/1/responsive/IMG_4882-xs.jpg",
        "type": "file",
        "md5": "ca75e7e8bff37dd4cb895125f437294b"
    },
    {
        "path": "/media/posts/1/responsive/IMG_4884-lg.jpg",
        "type": "file",
        "md5": "877ee8f6a5a9faff52935d84f6fbaaac"
    },
    {
        "path": "/media/posts/1/responsive/IMG_4884-md.jpg",
        "type": "file",
        "md5": "37ead173826544ccb78789d12412fa56"
    },
    {
        "path": "/media/posts/1/responsive/IMG_4884-sm.jpg",
        "type": "file",
        "md5": "2dcf8034e1289c5261dbb91cf769f721"
    },
    {
        "path": "/media/posts/1/responsive/IMG_4884-xs.jpg",
        "type": "file",
        "md5": "ff69545f89fc0a696d22a4e9e486fd99"
    },
    {
        "path": "media/website",
        "type": "directory",
        "md5": false
    },
    {
        "path": "/media/website/prfil.JPEG",
        "type": "file",
        "md5": "f53ff4f9fda8948ff14e523c3ff1660e"
    },
    {
        "path": "media/website/responsive",
        "type": "directory",
        "md5": false
    },
    {
        "path": "/media/website/responsive/prfil-2xl.JPEG",
        "type": "file",
        "md5": "90661e935942f1a3ffc4abe9c1e39fda"
    },
    {
        "path": "/media/website/responsive/prfil-lg.JPEG",
        "type": "file",
        "md5": "87fb3f9b412a6f8808a1660fa0f6de29"
    },
    {
        "path": "/media/website/responsive/prfil-md.JPEG",
        "type": "file",
        "md5": "226e3621f2959ecc98ba0c09e79792d8"
    },
    {
        "path": "/media/website/responsive/prfil-sm.JPEG",
        "type": "file",
        "md5": "314f583d2a84e40ea4691fac186abd74"
    },
    {
        "path": "/media/website/responsive/prfil-xl.JPEG",
        "type": "file",
        "md5": "597114a68fc9aa5eb6a83555fe3ba6b1"
    },
    {
        "path": "/media/website/responsive/prfil-xs.JPEG",
        "type": "file",
        "md5": "49530a1095ead51a61e8332cec3bcfce"
    },
    {
        "path": "robots.txt",
        "type": "file",
        "md5": "50d8a018e8ae96732c8a2ba663c61d4e"
    },
    {
        "path": "sarajevo.html",
        "type": "file",
        "md5": "ab71076cd7302785b57645a665868111"
    },
    {
        "path": "search.html",
        "type": "file",
        "md5": "d38f04c8bba7a38dde373b1beabce7ea"
    }
]